dictextendfuzzy/__init__.py
dictextendfuzzy/common.py
dictextendfuzzy/get_fuzzy.py
dictextendfuzzy/get_fuzzy_stats.py
dictextendfuzzy/magic.py
dict_extend_fuzzy-0.2.2.dist-info/LICENSE
dict_extend_fuzzy-0.2.2.dist-info/METADATA
dict_extend_fuzzy-0.2.2.dist-info/WHEEL
dict_extend_fuzzy-0.2.2.dist-info/entry_points.txt
dict_extend_fuzzy-0.2.2.dist-info/top_level.txt
dict_extend_fuzzy-0.2.2.dist-info/RECORD
