Metadata-Version: 2.1
Name: dict-extend-fuzzy
Version: 0.2.2
Summary: Get element by fuzzy key from dict
Home-page: https://github.com/devone-pl/dict-extend-fuzzy
Author: Kamil Hławiczka
Author-email: mail@devone.pl
License: MIT
Keywords: dict extend extension fuzzy fuzzykey
Platform: UNKNOWN
Classifier: Programming Language :: Python :: 3 :: Only
Classifier: Programming Language :: Python :: 3.4
Classifier: Programming Language :: Python :: 3.5
Classifier: Programming Language :: Python :: 3.6
Classifier: Programming Language :: Python :: 3.7
Classifier: Programming Language :: Python :: 3.8
Classifier: License :: OSI Approved :: MIT License
Classifier: Operating System :: OS Independent
